sphinx_documatt_theme/__init__.py
sphinx_documatt_theme/breadcrumb.html
sphinx_documatt_theme/globaltoc.html
sphinx_documatt_theme/layout.html
sphinx_documatt_theme/localtoc.html
sphinx_documatt_theme/theme.conf
sphinx_documatt_theme/static/css/main.css
sphinx_documatt_theme/static/css/main.css.map
sphinx_documatt_theme/static/img/external-link.png
sphinx_documatt_theme/static/img/favicon.ico
sphinx_documatt_theme/static/img/logo.svg
sphinx_documatt_theme/static/js/main.js
sphinx_documatt_theme-0.0.6.dist-info/LICENSE
sphinx_documatt_theme-0.0.6.dist-info/METADATA
sphinx_documatt_theme-0.0.6.dist-info/WHEEL
sphinx_documatt_theme-0.0.6.dist-info/entry_points.txt
sphinx_documatt_theme-0.0.6.dist-info/top_level.txt
sphinx_documatt_theme-0.0.6.dist-info/RECORD
