Metadata-Version: 2.1
Name: sphinx_documatt_theme
Version: 0.0.6
Summary: Documatt Theme for Sphinx documentation projects
Home-page: http://documatt.com/sphinx-themes/themes/documatt.html
Author: Documatt.com
Author-email: hello@documatt.com
License: BSD3
Classifier: Framework :: Sphinx
Classifier: Framework :: Sphinx :: Theme
Classifier: Development Status :: 5 - Production/Stable
Classifier: License :: OSI Approved :: MIT License
Classifier: Environment :: Console
Classifier: Environment :: Web Environment
Classifier: Intended Audience :: Developers
Classifier: Programming Language :: Python :: 3
Classifier: Operating System :: OS Independent
Classifier: Topic :: Documentation
Classifier: Topic :: Software Development :: Documentation
License-File: LICENSE
Requires-Dist: sphinx
